README.rst
setup.py
yandex_tracker_import/__init__.py
yandex_tracker_import.egg-info/PKG-INFO
yandex_tracker_import.egg-info/SOURCES.txt
yandex_tracker_import.egg-info/dependency_links.txt
yandex_tracker_import.egg-info/entry_points.txt
yandex_tracker_import.egg-info/requires.txt
yandex_tracker_import.egg-info/top_level.txt
yandex_tracker_import/cli/__init__.py
yandex_tracker_import/cli/main.py
yandex_tracker_import/src/__init__.py
yandex_tracker_import/src/data_mapping.py
yandex_tracker_import/src/hashing.py
yandex_tracker_import/src/importer.py
yandex_tracker_import/src/utils.py