Metadata-Version: 1.2
Name: yandex-tracker-import
Version: 0.6
Summary: move all your content to another organization
Home-page: UNKNOWN
Author: Vladimir Koljasinskij
Author-email: smosker@yandex-team.ru
License: BSD-3-Clause
Keywords: yandex-tracker import
Platform: UNKNOWN
Classifier: Development Status :: 4 - Beta
Classifier: Intended Audience :: Developers
Classifier: License :: OSI Approved :: BSD License
Classifier: Operating System :: OS Independent
Classifier: Topic :: Software Development :: Libraries :: Python Modules
Classifier: Programming Language :: Python
Classifier: Programming Language :: Python :: 3.7
Requires-Python: >=3.7
